resolution_aware_transformer/__init__.py
resolution_aware_transformer/resolution_aware_transformer.py
resolution_aware_transformer-2025.9.29.2036.dist-info/METADATA
resolution_aware_transformer-2025.9.29.2036.dist-info/WHEEL
resolution_aware_transformer-2025.9.29.2036.dist-info/licenses/LICENSE
resolution_aware_transformer-2025.9.29.2036.dist-info/RECORD
