Metadata-Version: 2.4
Name: resolution-aware-transformer
Version: 2025.9.29.2036
Summary: {{project_description}}
Project-URL: Homepage, https://github.com/rhoadesScholar/resolution-aware-transformer
Project-URL: Repository, https://github.com/rhoadesScholar/resolution-aware-transformer
Project-URL: Documentation, https://github.com/rhoadesScholar/resolution-aware-transformer
Project-URL: Issues, https://github.com/rhoadesScholar/resolution-aware-transformer/issues
Author-email: Jeff Rhoades <rhoadesj@alumni.harvard.edu>
Maintainer-email: Jeff Rhoades <rhoadesj@alumni.harvard.edu>
License: BSD 3-Clause License
License-File: LICENSE
Keywords: 3D,attention,computer vision,machine learning,python,pytorch,transformer
Classifier: Development Status :: 4 - Beta
Classifier: Intended Audience :: Developers
Classifier: Intended Audience :: Science/Research
Classifier: License :: OSI Approved :: BSD License
Classifier: Operating System :: OS Independent
Classifier: Programming Language :: Python :: 3
Classifier: Programming Language :: Python :: 3.10
Classifier: Programming Language :: Python :: 3.11
Classifier: Programming Language :: Python :: 3.12
Classifier: Topic :: Scientific/Engineering
Classifier: Topic :: Software Development :: Libraries :: Python Modules
Requires-Python: >=3.10
Requires-Dist: rotary-spatial-embeddings>=2025.9.25.1502
Requires-Dist: spatial-grouping-attention>=2025.9.29.1947
Requires-Dist: torch
Provides-Extra: dev
Requires-Dist: black>=22.0; extra == 'dev'
Requires-Dist: flake8>=4.0; extra == 'dev'
Requires-Dist: isort>=5.0; extra == 'dev'
Requires-Dist: mypy>=0.900; extra == 'dev'
Requires-Dist: pre-commit>=2.0; extra == 'dev'
Requires-Dist: pytest-cov>=2.0; extra == 'dev'
Requires-Dist: pytest-xdist>=2.0; extra == 'dev'
Requires-Dist: pytest>=6.0; extra == 'dev'
Provides-Extra: docs
Requires-Dist: myst-parser>=0.15; extra == 'docs'
Requires-Dist: sphinx-rtd-theme>=1.0; extra == 'docs'
Requires-Dist: sphinx>=4.0; extra == 'docs'
Provides-Extra: experiments
Requires-Dist: deepspeed>=0.5; extra == 'experiments'
Requires-Dist: matplotlib>=3.4; extra == 'experiments'
Requires-Dist: numpy>=1.20; extra == 'experiments'
Requires-Dist: pandas>=1.3; extra == 'experiments'
Requires-Dist: pillow>=8.0; extra == 'experiments'
Requires-Dist: pyyaml>=5.4; extra == 'experiments'
Requires-Dist: ray[train]; extra == 'experiments'
Requires-Dist: requests>=2.25; extra == 'experiments'
Requires-Dist: scikit-learn>=1.0; extra == 'experiments'
Requires-Dist: seaborn>=0.11; extra == 'experiments'
Requires-Dist: tensorboard>=2.8; extra == 'experiments'
Requires-Dist: torchmetrics[detection]; extra == 'experiments'
Requires-Dist: tqdm>=4.0; extra == 'experiments'
Provides-Extra: lint
Requires-Dist: black>=22.0; extra == 'lint'
Requires-Dist: flake8>=4.0; extra == 'lint'
Requires-Dist: isort>=5.0; extra == 'lint'
Requires-Dist: mypy>=0.900; extra == 'lint'
Provides-Extra: test
Requires-Dist: pytest-cov>=2.0; extra == 'test'
Requires-Dist: pytest-xdist>=2.0; extra == 'test'
Requires-Dist: pytest>=6.0; extra == 'test'
